lenstest/__init__.py
lenstest/foucault.py
lenstest/lenstest.py
lenstest/ronchi.py
lenstest-1.0.1.dist-info/licenses/LICENSE.txt
lenstest-1.0.1.dist-info/METADATA
lenstest-1.0.1.dist-info/WHEEL
lenstest-1.0.1.dist-info/top_level.txt
lenstest-1.0.1.dist-info/RECORD
